{
  "project_info": {
    "project_number": "114498280376",
    "project_id": "buffer-54c74",
    "storage_bucket": "buffer-54c74.appspot.com"
  },
  "client": [
    {
      "client_info": {
        "mobilesdk_app_id": "1:114498280376:android:a117c27cfeb5f172564d4d",
        "android_client_info": {
          "package_name": "com.example.buffer"
        }
      },
      "oauth_client": [
        {
          "client_id": "114498280376-12alut17cogecslaurekbequoea9epo9.apps.googleusercontent.com",
          "client_type": 1,
          "android_info": {
            "package_name": "com.example.buffer",
            "certificate_hash": "914e89e3257da6efb7f6fa66f0dd2e3d5770c2b8"
          }
        },
        {
          "client_id": "114498280376-42r29pu3k4p2eok8uf9ur57s8tqajv6v.apps.googleusercontent.com",
          "client_type": 3
        }
      ],
      "api_key": [
        {
          "current_key": "AIzaSyA9bz8jNNmrYDHWMDOF-JzOSxYeEBAdoFc"
        }
      ],
      "services": {
        "appinvite_service": {
          "other_platform_oauth_client": [
            {
              "client_id": "114498280376-42r29pu3k4p2eok8uf9ur57s8tqajv6v.apps.googleusercontent.com",
              "client_type": 3
            }
          ]
        }
      }
    }
  ],
  "configuration_version": "1"
}